soundmentations/__init__.py
soundmentations/core/__init__.py
soundmentations/core/composition.py
soundmentations/core/transforms_interface.py
soundmentations/transforms/__init__.py
soundmentations/transforms/amplitude/__init__.py
soundmentations/transforms/amplitude/compressor.py
soundmentations/transforms/amplitude/fade.py
soundmentations/transforms/amplitude/gain.py
soundmentations/transforms/amplitude/limiter.py
soundmentations/transforms/effects/__init__.py
soundmentations/transforms/effects/delay.py
soundmentations/transforms/frequency/__init__.py
soundmentations/transforms/frequency/equalizers.py
soundmentations/transforms/frequency/filters.py
soundmentations/transforms/frequency/formant_shift.py
soundmentations/transforms/frequency/pitch_shift.py
soundmentations/transforms/noise/__init__.py
soundmentations/transforms/noise/generators.py
soundmentations/transforms/time/__init__.py
soundmentations/transforms/time/mask.py
soundmentations/transforms/time/pad.py
soundmentations/transforms/time/trim.py
soundmentations/utils/__init__.py
soundmentations/utils/audio.py
soundmentations-0.1.0.dist-info/licenses/LICENSE
soundmentations-0.1.0.dist-info/METADATA
soundmentations-0.1.0.dist-info/WHEEL
soundmentations-0.1.0.dist-info/top_level.txt
soundmentations-0.1.0.dist-info/RECORD
