Metadata-Version: 2.4
Name: soundmentations
Version: 0.1.0
Summary: Soundmentations: A Python library for sound classification and augmentation
Home-page: https://github.com/saumyarr8/soundmentations
Author: Saumya Ranjan
Author-email: saumyarr8@outlook.com
License: MIT
Keywords: sound,classification,augmentation,machine learning
Classifier: Programming Language :: Python :: 3
Classifier: License :: OSI Approved :: MIT License
Classifier: Topic :: Scientific/Engineering :: Artificial Intelligence
Classifier: Topic :: Software Development :: Libraries :: Python Modules
Classifier: Topic :: Multimedia :: Sound/Audio
Classifier: Topic :: Multimedia :: Sound/Audio :: Analysis
Requires-Python: >=3.9
License-File: LICENSE
Requires-Dist: numpy>=2.0.0
Requires-Dist: scipy>=1.0.0
Requires-Dist: librosa>=0.10.0
Requires-Dist: soundfile>=0.10.0
Provides-Extra: docs
Requires-Dist: sphinx>=7.0.0; extra == "docs"
Requires-Dist: sphinx-copybutton>=0.5.0; extra == "docs"
Requires-Dist: furo>=2024.08.06; extra == "docs"
Dynamic: license-file
